maclookupcli/__init__.py
maclookupcli/command.py
maclookupcli/utilities.py
maclookupcli/errors/__init__.py
maclookupcli/errors/fatal_error.py
maclookupcli/errors/ignorable_error.py
maclookup_cli-0.1.9.dist-info/LICENSE
maclookup_cli-0.1.9.dist-info/METADATA
maclookup_cli-0.1.9.dist-info/WHEEL
maclookup_cli-0.1.9.dist-info/entry_points.txt
maclookup_cli-0.1.9.dist-info/top_level.txt
maclookup_cli-0.1.9.dist-info/RECORD
