Metadata-Version: 2.1
Name: maclookup-cli
Version: 0.1.9
Summary: Console tool to make a MAC vendor lookups
Home-page: https://github.com/CodeLineFi/maclookup-cli
Author: CodeLine OY
Author-email: support@macaddress.io
License: MIT
Platform: UNKNOWN
Classifier: License :: OSI Approved :: MIT License
Classifier: Operating System :: Unix
Classifier: Operating System :: POSIX
Classifier: Operating System :: Microsoft :: Windows
Classifier: Programming Language :: Python
Classifier: Programming Language :: Python :: 2.7
Classifier: Programming Language :: Python :: 3
Classifier: Programming Language :: Python :: 3.6
Classifier: Programming Language :: Python :: Implementation :: CPython
Requires-Dist: click
Requires-Dist: maclookup
